autojob/__about__.py
autojob/__init__.py
autojob/__main__.py
autojob/hpc.py
autojob/parametrizations.py
autojob/py.typed
autojob/schemas.py
autojob/settings.py
autojob/study.py
autojob/study_group.py
autojob/task.py
autojob/workflow.py
autojob/advance/__init__.py
autojob/advance/advance.py
autojob/calculation/__init__.py
autojob/calculation/calculation.py
autojob/calculation/calculators.py
autojob/calculation/gaussian.py
autojob/calculation/infrared.py
autojob/calculation/parameters.py
autojob/calculation/vibration.py
autojob/calculation/vasp/__init__.py
autojob/calculation/vasp/defaults.py
autojob/calculation/vasp/vasp.py
autojob/cli/__init__.py
autojob/cli/advance.py
autojob/cli/init.py
autojob/cli/main.py
autojob/cli/restart_relaxation.py
autojob/cli/run_vibration.py
autojob/cli/utils.py
autojob/coordinator/__init__.py
autojob/coordinator/classification.py
autojob/coordinator/cli.py
autojob/coordinator/coordinator.py
autojob/coordinator/gaussian.py
autojob/coordinator/job.py
autojob/coordinator/scripter.py
autojob/coordinator/validation.py
autojob/coordinator/vasp.py
autojob/coordinator/gui/__init__.py
autojob/coordinator/gui/groups.py
autojob/coordinator/gui/gui.py
autojob/coordinator/gui/job_submission.py
autojob/coordinator/gui/parameter_selection.py
autojob/coordinator/gui/structure_selection.py
autojob/coordinator/gui/study_configuration.py
autojob/coordinator/gui/submission_configuration.py
autojob/coordinator/gui/summary.py
autojob/coordinator/gui/widgets.py
autojob/harvest/__init__.py
autojob/harvest/archive.py
autojob/harvest/charge.py
autojob/harvest/cli.py
autojob/harvest/harvest.py
autojob/harvest/mechanism.py
autojob/harvest/metadata.py
autojob/harvest/patch.py
autojob/harvest/structure.py
autojob/next/__init__.py
autojob/next/relaxation.py
autojob/next/vibration.py
autojob/templates/ase_relaxation.run.py.j2
autojob/templates/hubbard.run.py.j2
autojob/templates/infrared.py.j2
autojob/templates/relaxation.py.j2
autojob/templates/run.py.j2
python_autojob-0.12.0b1.dist-info/METADATA
python_autojob-0.12.0b1.dist-info/WHEEL
python_autojob-0.12.0b1.dist-info/entry_points.txt
python_autojob-0.12.0b1.dist-info/licenses/AUTHORS.rst
python_autojob-0.12.0b1.dist-info/licenses/LICENSE
python_autojob-0.12.0b1.dist-info/RECORD
